empyer/__init__.py
empyer/io.py
empyer/misc/__init__.py
empyer/misc/angular_correlation.py
empyer/misc/cartesain_to_polar.py
empyer/misc/ellipse_analysis.py
empyer/misc/fem.py
empyer/misc/image.py
empyer/signals/__init__.py
empyer/signals/correlation_signal.py
empyer/signals/diffraction_signal.py
empyer/signals/em_signal.py
empyer/signals/polar_signal.py
empyer/signals/power_signal.py
empyer/simulate/__init__.py
empyer/tests/__init__.py
empyer-0.12.dist-info/METADATA
empyer-0.12.dist-info/WHEEL
empyer-0.12.dist-info/top_level.txt
empyer-0.12.dist-info/RECORD
