Metadata-Version: 2.1
Name: empyer
Version: 0.12
Summary: Electron Microscopy tools for analyzing 4 and 5 dimensional STEM datasets
Home-page: https://github.com/CSSFrancis/empyer
Author: CSSFrancis
Author-email: csfrancis@wisc.edu
License: UNKNOWN
Keywords: STEM Electron Microscopy Glass
Platform: UNKNOWN
Requires-Dist: hyperspy (>=1.3)
Requires-Dist: numpy
Requires-Dist: matplotlib
